docker_rb/__init__.py
docker_rb/cli.py
docker_rb/dockerapi.py
docker_rb/utils.py
docker_run_build-0.1.1.dist-info/DESCRIPTION.rst
docker_run_build-0.1.1.dist-info/entry_points.txt
docker_run_build-0.1.1.dist-info/METADATA
docker_run_build-0.1.1.dist-info/metadata.json
docker_run_build-0.1.1.dist-info/pbr.json
docker_run_build-0.1.1.dist-info/RECORD
docker_run_build-0.1.1.dist-info/top_level.txt
docker_run_build-0.1.1.dist-info/WHEEL
