Metadata-Version: 2.0
Name: docker-run-build
Version: 0.1.1
Summary: Incrementally build Docker images
Home-page: http://github.com/caioariede/docker-run-build
Author: Caio Ariede
Author-email: caio.ariede@gmail.com
License: MIT
Platform: any
Classifier: Intended Audience :: Developers
Classifier: License :: OSI Approved :: MIT License
Classifier: Operating System :: OS Independent
Classifier: Programming Language :: Python
Classifier: Programming Language :: Python :: 3
Classifier: Programming Language :: Python :: 3.4
Requires-Dist: six
Requires-Dist: docker-py (==1.6.0)
Requires-Dist: click (==6.2)
